<?xml version="1.0" encoding="UTF-8"?>
<strokes>
<stroke>
<name>Line</name>
<width>1.0</width>
<cap>2</cap>
<join>2</join>
<miterlimit>10.0</miterlimit>
<dash>1.0,0.0</dash>
<dashphase>0.0</dashphase>
</stroke>
<stroke>
<name>Dash</name>
<width>1.0</width>
<cap>2</cap>
<join>2</join>
<miterlimit>10.0</miterlimit>
<dash>4.0,2.0</dash>
<dashphase>0.0</dashphase>
</stroke>
<stroke>
<name>Dot</name>
<width>1.0</width>
<cap>2</cap>
<join>2</join>
<miterlimit>10.0</miterlimit>
<dash>1.0,2.0</dash>
<dashphase>0.0</dashphase>
</stroke>
</strokes>
